fastapi_router/__init__.py
fastapi_router/main.py
fastapi_router-0.0.5.dist-info/METADATA
fastapi_router-0.0.5.dist-info/WHEEL
fastapi_router-0.0.5.dist-info/RECORD
