Metadata-Version: 2.1
Name: fastapi-router
Version: 0.0.5
Summary: Fastapi like Next.js. Efficient Backend, Agile Development.
Author: Kevin Kener
Author-email: kevink.contacto@gmail.com
Requires-Python: >=3.11,<4.0
Classifier: Programming Language :: Python :: 3
Classifier: Programming Language :: Python :: 3.11
Classifier: Programming Language :: Python :: 3.12
Requires-Dist: fastapi (>=0.104.1,<0.105.0)
Requires-Dist: uvicorn (>=0.24.0.post1,<0.25.0)
